{
	"_id": "0vRwhfQgvAkzToHN",
	"_key": "!tables!0vRwhfQgvAkzToHN",
	"description": "",
	"displayRoll": true,
	"folder": "nvmUa5zF3reHgMlg",
	"formula": "2d6",
	"img": "icons/equipment/head/hood-purple-mask.webp",
	"name": "Class Talents: Ras-Godai",
	"replacement": true,
	"results": [
		"JtyvVAqYv6AOTZAG",
		"j2cUqus95ATrII4E",
		"tGZ1qLefW5q6dCnG",
		"RX3hqCehCxrwsYbe",
		"PaRSmTRors92vNHj",
		"X8kbXADMeDvMGVen",
		"RPesdhBtzQyC2KTy",
		"shAiehdgKTq4SHkE",
		"U6dngSSFFxKUNeKU",
		"TTKzmcpfzqCFofN8",
		"Ok9QceTSSYP7XgSq",
		"KC2csh2be1TzEcwq",
		"j0zaAW1vY7lVA4Vy"
	]
}
