{
  "name": "Roll Random Character",
  "img": "icons/environment/people/group.webp",
  "description": "- Pick one Weapon (See Weapons compendium)\n- Pick Leather Armor if you can wear it (See Armor compendium)",
  "results": [
    {
      "type": 2,
      "weight": 1,
      "range": [
        1,
        1
      ],
      "drawn": false,
      "text": "Random Alignment",
      "img": "icons/environment/people/group.webp",
      "documentCollection": "shadowdark.rollable-tables",
      "documentId": "TJCChWMoFSEf9qhK",
      "_id": "9GrvqyPrqFuLM46C",
      "flags": {}
    },
    {
      "type": 2,
      "weight": 1,
      "range": [
        1,
        1
      ],
      "drawn": false,
      "text": "Random Ancestry",
      "img": "icons/environment/people/group.webp",
      "documentCollection": "shadowdark.rollable-tables",
      "documentId": "ljbaTPUHqeNzyM2b",
      "_id": "EJSTyXp75GftHgdd",
      "flags": {}
    },
    {
      "type": 2,
      "weight": 1,
      "range": [
        1,
        1
      ],
      "drawn": false,
      "text": "Random Class",
      "img": "icons/environment/people/group.webp",
      "documentCollection": "shadowdark.rollable-tables",
      "documentId": "mMgcf5V3voQSvrdr",
      "_id": "fWby9eYWxd1XneDg",
      "flags": {}
    },
    {
      "type": 2,
      "weight": 1,
      "range": [
        1,
        1
      ],
      "drawn": false,
      "text": "Random Gear Rolls",
      "img": "icons/environment/people/group.webp",
      "documentCollection": "shadowdark.rollable-tables",
      "documentId": "3158XkwQAHF20RJQ",
      "_id": "bTx7SDbteDwOT0wj",
      "flags": {}
    }
  ],
  "formula": "1",
  "replacement": true,
  "displayRoll": true,
  "ownership": {
    "default": 0,
    "EKVggA45fx6fzkCK": 3
  },
  "flags": {
    "core": {
      "sourceId": "RollTable.BCqteRNz3mlDKjHN"
    }
  },
  "_stats": {
    "systemId": "shadowdark",
    "systemVersion": "0.1.0",
    "coreVersion": "10.291",
    "createdTime": 1679418209556,
    "modifiedTime": 1679462242049,
    "lastModifiedBy": "xfit8sRhRTooADjZ"
  },
  "folder": null,
  "sort": 0,
  "_id": "IHpIMJy4xdXZnPFy"
}