{
	"_id": "LR6h4lXVXwx7AFQ6",
	"effects": [
		{
			"_id": "iR3hHoX6W9VOCfy0",
			"changes": [
				{
					"key": "system.bonuses.meleeAttackBonus",
					"mode": 2,
					"priority": null,
					"value": "1"
				}
			],
			"disabled": false,
			"duration": {
				"combat": null,
				"rounds": null,
				"seconds": null,
				"startRound": null,
				"startTime": null,
				"startTurn": null,
				"turns": null
			},
			"flags": {
			},
			"icon": "icons/skills/melee/strike-polearm-glowing-white.webp",
			"label": "Melee Attack Roll Bonus",
			"origin": null,
			"tint": null,
			"transfer": true
		},
		{
			"_id": "9LnTbRJXNUH9wLTy",
			"changes": [
				{
					"key": "system.bonuses.meleeDamageBonus",
					"mode": 2,
					"priority": null,
					"value": "1"
				}
			],
			"disabled": false,
			"duration": {
				"combat": null,
				"rounds": null,
				"seconds": null,
				"startRound": null,
				"startTime": null,
				"startTurn": null,
				"turns": null
			},
			"flags": {
			},
			"icon": "icons/skills/melee/strike-axe-blood-red.webp",
			"label": "Melee Damage Bonus",
			"origin": null,
			"tint": null,
			"transfer": true
		}
	],
	"img": "icons/skills/melee/strike-axe-blood-red.webp",
	"name": "Mighty",
	"system": {
		"bonuses": {
			"meleeAttackBonus": "1",
			"meleeDamageBonus": "1"
		},
		"description": "<p>You have a +1 bonus to attack and damage rolls with melee weapons.</p>",
		"level": 1,
		"magicItem": false,
		"predefinedEffects": "",
		"properties": [
			"meleeAttackBonus",
			"meleeDamageBonus"
		],
		"talentClass": "ancestry"
	},
	"type": "Talent"
}
