{
	"_id": "XmlEQByLpzXULngp",
	"_key": "!actors.items.effects!4gxXdPgUd0ofz89A.q4XASzehX7TfLgjb.XmlEQByLpzXULngp",
	"changes": [
		{
			"key": "system.bonuses.weaponMastery",
			"mode": 2,
			"priority": null,
			"value": "bastard-sword"
		}
	],
	"description": "",
	"disabled": false,
	"duration": {
		"combat": null,
		"rounds": null,
		"seconds": null,
		"startRound": null,
		"startTime": null,
		"startTurn": null,
		"turns": null
	},
	"icon": "icons/skills/melee/weapons-crossed-swords-white-blue.webp",
	"name": "Weapon Mastery",
	"origin": null,
	"statuses": [
	],
	"tint": null,
	"transfer": true
}
