{
	"_id": "8F6hv1kM20gcNZOM",
	"_key": "!actors.effects!4gxXdPgUd0ofz89A.8F6hv1kM20gcNZOM",
	"changes": [
		{
			"key": "system.roll.melee.bonus.bastard-sword",
			"mode": 2,
			"priority": null,
			"value": "1+floor(@level.value/2)"
		},
		{
			"key": "system.roll.melee.damage.bastard-sword",
			"mode": 2,
			"value": "1+floor(@level.value/2)"
		}
	],
	"description": "",
	"disabled": false,
	"duration": {
		"combat": null,
		"rounds": null,
		"seconds": null,
		"startRound": null,
		"startTime": 788,
		"startTurn": null,
		"turns": null
	},
	"img": "icons/skills/melee/weapons-crossed-swords-white-blue.webp",
	"name": "Weapon Mastery",
	"origin": "Actor.4gxXdPgUd0ofz89A.Item.q4XASzehX7TfLgjb",
	"statuses": [
	],
	"system": {
	},
	"tint": "#ffffff",
	"transfer": false,
	"type": "base"
}
