{
	"_id": "9vBMOVy2rmyRnHUY",
	"_key": "!items!9vBMOVy2rmyRnHUY",
	"effects": [
	],
	"folder": "EGzgHJF6jewvtHDZ",
	"img": "icons/skills/trades/academics-merchant-scribe.webp",
	"name": "Naming",
	"system": {
		"class": [
			"Compendium.shadowdark.classes.Item.NGJJVaEujQVOg13j"
		],
		"description": "<p>You learn the True Name (Shadowdark RPG pg. 319) of one creature you touch.</p><p>If the creature is willing, you may give it a new True Name. A creature may only change its True Name once in its lifetime.</p><p>If it does so, its alignment changes to your alignment.</p>",
		"duration": {
			"type": "instant",
			"value": 1
		},
		"lost": false,
		"range": "close",
		"source": {
			"title": "cursed-scroll-4"
		},
		"tier": 5
	},
	"type": "Spell"
}
