{
	"_id": "Mdq3WUCNo0tSog0C",
	"_key": "!items!Mdq3WUCNo0tSog0C",
	"effects": [
	],
	"folder": "GQzGt69sWAwFKfnv",
	"img": "icons/magic/sonic/scream-wail-shout-teal.webp",
	"name": "Truespeech",
	"system": {
		"class": [
			"Compendium.shadowdark.classes.Item.NGJJVaEujQVOg13j"
		],
		"description": "<p>A natural creature you touch understands and can communicate with you in the true language of all animals.</p><p>You can ask the creature one yes or no question. The GM truthfully answers \"yes\" or \"no.\"</p><p>If you cast this spell more than once on the same creature in 24 hours, treat a failed spellcasting check for it as a critical failure instead.</p>",
		"duration": {
			"type": "instant",
			"value": 1
		},
		"lost": false,
		"range": "close",
		"source": {
			"title": "cursed-scroll-4"
		},
		"tier": 1
	},
	"type": "Spell"
}
