{
	"_id": "uzQh5r9z2SlQKu7A",
	"_key": "!actors.items!vVRAwuWbYEtPctOE.uzQh5r9z2SlQKu7A",
	"effects": [
	],
	"folder": null,
	"img": "icons/skills/melee/weapons-crossed-swords-yellow.webp",
	"name": "Bite",
	"system": {
		"attack": {
			"num": "2"
		},
		"attackType": "physical",
		"bonuses": {
			"attackBonus": 5,
			"critical": {
				"failureThreshold": 1,
				"multiplier": 2,
				"successThreshold": 20
			},
			"damageBonus": 0
		},
		"damage": {
			"numDice": "2",
			"special": "",
			"value": "2d8"
		},
		"description": "",
		"ranges": [
			"close"
		],
		"source": {
			"title": ""
		}
	},
	"type": "NPC Attack"
}
